mzemail/__init__.py
mzemail/email_sender.py
mzemail-0.1.1.dist-info/LICENSE.txt
mzemail-0.1.1.dist-info/METADATA
mzemail-0.1.1.dist-info/WHEEL
mzemail-0.1.1.dist-info/top_level.txt
mzemail-0.1.1.dist-info/RECORD
